hola.py
hola_paq-0.0.1.dist-info/METADATA
hola_paq-0.0.1.dist-info/WHEEL
hola_paq-0.0.1.dist-info/top_level.txt
hola_paq-0.0.1.dist-info/RECORD
