Metadata-Version: 2.1
Name: hola-paq
Version: 0.0.1
Summary: Another hello-world example package
Home-page: UNKNOWN
Author: Miguel López Cruz
Author-email: miguellcl@hotmail.com
License: UNKNOWN
Platform: UNKNOWN
Classifier: Programming Language :: Python :: 3
Classifier: License :: OSI Approved :: MIT License
Classifier: Operating System :: OS Independent
